sphinterp/__init__.py
sphinterp/_coordinates.py
sphinterp/_cross_section.py
sphinterp/_kernels.py
sphinterp/_projection.py
sphinterp-0.0.1.dist-info/LICENSE
sphinterp-0.0.1.dist-info/METADATA
sphinterp-0.0.1.dist-info/WHEEL
sphinterp-0.0.1.dist-info/top_level.txt
sphinterp-0.0.1.dist-info/RECORD
