Metadata-Version: 2.1
Name: sphinterp
Version: 0.0.1
Summary: Smoothed particle hydrodynamics interpolation to a grid.
Home-page: https://github.com/dmentipl/sph-interp
Author: Daniel Mentiplay
Author-email: d.mentiplay@gmail.com
License: MIT
Platform: UNKNOWN
Classifier: Development Status :: 2 - Pre-Alpha
Classifier: License :: OSI Approved :: GNU General Public License v2 (GPLv2)
Classifier: Programming Language :: Python :: 3.6
Classifier: Programming Language :: Python :: 3.7
Classifier: Programming Language :: Python :: 3.8
Classifier: Operating System :: OS Independent
Classifier: Topic :: Scientific/Engineering :: Astronomy
Classifier: Topic :: Scientific/Engineering :: Visualization
Requires-Dist: numba
Requires-Dist: numpy
